curedcolumns/__init__.py
curedcolumns/__main__.py
curedcolumns/exceptions.py
curedcolumns/get_s3_parquet_schema.py
curedcolumns/iter_files.py
curedcolumns-0.1.2.dist-info/LICENSE
curedcolumns-0.1.2.dist-info/METADATA
curedcolumns-0.1.2.dist-info/WHEEL
curedcolumns-0.1.2.dist-info/entry_points.txt
curedcolumns-0.1.2.dist-info/top_level.txt
curedcolumns-0.1.2.dist-info/RECORD
