Metadata-Version: 2.1
Name: curedcolumns
Version: 0.1.2
Summary: CUREd+ metadata tool: generates a list of all the columns in every table in the database.
License: MIT License
Project-URL: Homepage, https://www.sheffield.ac.uk/data-connect
Project-URL: Bug_Tracker, https://github.com/CUREd-Plus/curedcolumns/issues
Project-URL: Documentation, https://github.com/CUREd-Plus/curedcolumns/blob/main/README.md
Project-URL: Repository, https://github.com/CUREd-Plus/curedcolumns
Project-URL: Changelog, https://github.com/CUREd-Plus/curedcolumns/releases
License-File: LICENSE
Requires-Dist: boto3 ==1.*
Requires-Dist: pyarrow ==16.*
Requires-Dist: boto3-type-annotations ==0.*
Provides-Extra: test
Requires-Dist: pytest ==8.* ; extra == 'test'
Requires-Dist: moto[s3] ==5.* ; extra == 'test'
